{
  "parent": "minecraft:recipes/root",
  "criteria": {
    "has_the_recipe": {
      "conditions": {
        "recipe": "bartending:emptying/coffee_liqueur"
      },
      "trigger": "minecraft:recipe_unlocked"
    },
    "obtain_input": {
      "conditions": {
        "items": [
          {
            "items": [
              "bartending:coffee_liqueur"
            ]
          }
        ]
      },
      "trigger": "minecraft:inventory_changed"
    }
  },
  "requirements": [
    [
      "obtain_input",
      "has_the_recipe"
    ]
  ],
  "rewards": {
    "recipes": [
      "bartending:emptying/coffee_liqueur"
    ]
  },
  "sends_telemetry_event": false
}